{
  "kind": "singleType",
  "collectionName": "contents",
  "info": {
    "name": "content",
    "displayName": "Содержимое сайта",
    "description": ""
  },
  "options": {
    "increments": true,
    "timestamps": true,
    "draftAndPublish": true
  },
  "pluginOptions": {},
  "attributes": {
    "sections": {
      "type": "dynamiczone",
      "components": [
        "section.section-hero",
        "section.section-catalog",
        "section.section-about",
        "section.section-clients",
        "section.section-feedbak"
      ]
    }
  }
}
